govpack/__init__.py
govpack/create_var.py
govpack-0.1.1.dist-info/LICENSE
govpack-0.1.1.dist-info/METADATA
govpack-0.1.1.dist-info/WHEEL
govpack-0.1.1.dist-info/top_level.txt
govpack-0.1.1.dist-info/RECORD
