Metadata-Version: 2.1
Name: govpack
Version: 0.1.1
Summary: A package that helps to create pandas variables from a public datasets: https://data.gov.ua/ 
Home-page: https://github.com/ThatAIGeek/govpack
Author: Yaroslav Khoruzhenko, Andrii Boiichuk
Author-email: yarusx@gmail.com
License: UNKNOWN
Platform: UNKNOWN
Classifier: Programming Language :: Python :: 3
Classifier: License :: OSI Approved :: MIT License
Classifier: Operating System :: OS Independent
Requires-Python: >=3.6
Requires-Dist: pandas
Requires-Dist: xlrd (==1.2.0)
